crumpy/__init__.py
crumpy/bundle.js
crumpy/py.typed
crumpy-0.2.0.dist-info/LICENSE
crumpy-0.2.0.dist-info/METADATA
crumpy-0.2.0.dist-info/NOTICE
crumpy-0.2.0.dist-info/WHEEL
crumpy-0.2.0.dist-info/RECORD
