Metadata-Version: 2.3
Name: crumpy
Version: 0.2.0
Summary: A python library for visualizing Crumble circuits in Jupyter
Author: Riverlane
Author-email: deltakit@riverlane.com
Requires-Python: >=3.11
Classifier: Development Status :: 1 - Planning
Classifier: Intended Audience :: Science/Research
Classifier: Intended Audience :: Developers
Classifier: Operating System :: OS Independent
Classifier: Programming Language :: Python
Classifier: Programming Language :: Python :: 3
Classifier: Programming Language :: Python :: 3 :: Only
Classifier: Programming Language :: Python :: 3.11
Classifier: Programming Language :: Python :: 3.12
Classifier: Programming Language :: Python :: 3.13
Classifier: Topic :: Scientific/Engineering
Classifier: Typing :: Typed
Requires-Dist: anywidget (>=0.9.18)
Requires-Dist: cirq (>=1.3.0)
Requires-Dist: ipywidgets (>=8.1.7)
Requires-Dist: ply (>=3.11)
Requires-Dist: qiskit (>=2.1.2)
Requires-Dist: stim (>=1.15.0)
Requires-Dist: stimcirq (>=1.15.0)
Requires-Dist: traitlets (>=5.14.3)
Project-URL: Bug Tracker, https://github.com/Deltakit/crumpy/issues
Project-URL: Changelog, https://github.com/Deltakit/crumpy/releases
Project-URL: Discussions, https://github.com/Deltakit/crumpy/discussions
Project-URL: Homepage, https://github.com/Deltakit/crumpy
